{
  "id": "com.unloadvsd",
  "name": "unloadVSD",
  "latest": "1.0",
  "repository": "dpkg9510's Repo",
  "url": "http://cydia.saurik.com/package/com.unloadvsd/",
  "shortDescription": "Unloads Videosupscriptionsd whenever you’re jailbroken.",
  "category": "Utilities",
  "author": "dpkg_",
  "commercial": false,
  "date": "2018-10-20T04:53:24Z",
  "versions": [
    {
      "tweakVersion": "1.0",
      "iOSVersion": "11.3.1",
      "repository": "dpkg9510's Repo",
      "date": "2018-10-20T04:53:24Z",
      "outcome": {
        "calculatedStatus": "Working",
        "percentage": 100,
        "good": 2,
        "bad": 0,
        "total": 2,
        "arch32": {
          "total": 0,
          "good": 0,
          "bad": 0,
          "percentage": 0,
          "calculatedStatus": "Unknown"
        }
      },
      "users": [
        {
          "status": "working",
          "device": "iPhone8,4",
          "issues": "",
          "date": "2018-10-20T04:53:24Z",
          "userName": "j0k3r",
          "issueNumber": 53424,
          "arch32": false
        },
        {
          "status": "working",
          "device": "iPhone7,1",
          "issues": "",
          "date": "2018-10-20T08:52:39Z",
          "userName": "gggomg",
          "issueNumber": 53440,
          "arch32": false
        }
      ]
    }
  ]
}
